Workbook

Sheet Поступления
A1: категории поступлений | B1: Продажи текущие | C1: Продажи контракт | D1: Спецпроект | E1: Кредит | F1: Возвраты от поставщиков | G1: Нераспределенное | H1: Прочие поступл. от фин. операций
A2: подкатегории | B2: КИВИ Кейтеринг | C2: ЯРОД (контракт) | D2: Строители Олонхо
B3: КИВИ Ивент | C3: РБ2 (контракт) | D3: Кобяйская СОШ (лагерь)
B4: КИВИ Деливери | C4: Школа №7 (контракт) | D4: Прочие спецпроекты
B5: КИВИ фит | C5: Школа №21 (контракт)
B6: РЦ буфет | C6: Школа №26 (контракт)
B7: РСКШИ буфет | C7: Айыы кыьата (контракт)
B8: Речевая буфет | C8: Речевая (контракт)
B9: Кытылга | C9: РЦ (контракт)
B10: Школа №7 | C10: РСКШИ (контракт)
B11: Школа №21 | C11: ДИКБ (контракт)
B12: Школа №26
B13: Айыы кыьата
B14: Дебиторская задолженность покупателей

Sheet Расходы
A1: Группы
A2: Обязательные
B3: Прочие | C3: Банк | D3: Налог | E3: Помещения | F3: Транспорт
B4: Агентские вознаграждения | C4: Банковское обслуживание | D4: Налог на доходы | E4: Оплата аренды и ВКУ | F4: Топливо
B5: Агрегаторы | C5: Комиссия по эквайрингу | D5: Налог ФОТ | E5: Услуги связи и интернета | F5: Услуги такси/Развоз персонала
B6: Расходы на программное обеспечение | C6: Погашение кредитов
A7: Переменные
B8: Рекламный бюджет | C8: Себестоимость | D8: Кредиторка | E8: Вывод прибыли (дивиденды) | F8: Возврат клиентам | G8: Налоги ФОТ
C9: Закуп сырья | D9: Кредиторка по аренде | H9: Официанты
C10: Зарплата | D10: Кредиторка по рекламе | H10: Транспортные услуги
D11: Кредиторка по сырью | H11: Транспортные расходы
H12: Фриланс
A13: Непостоянные платежи
B14: Прочее | C14: Расходы персонала | D14: Гос платежи | E14: Подрядчики | F14: Непредвиденные расходы
B15: ОС и ТМЦ | C15: Спецодежда | D15: Участие на тендерах | E15: Административные подрядчики
B16: Содержание объектов | C16: Канцтовары | D16: Платежи в бюджет | E16: Услуги сторонних подрядчиков
B17: Стратсессии | C17: Командировочные | D17: Производственный контроль (СЭС) | E17: Производственные подрядчики
C18: Медосмотры
C19: Представительские расходы
C20: Поиск и найм персонала

Sheet Сопоставление
A1: Названия в финтабло | C1: Название в таблице фондов
A2: Статья | B2: Род. статья
A3: Агентские вознаграждения | C3: Агентские вознаграждения
A4: Агрегаторы | C4: Агрегаторы
A5: Административные подрядчики | C5: Административные подрядчики
A6: Банковское обслуживание | C6: Банковское обслуживание
A7: Возврат клиентам | C7: Возврат клиентам
A8: Вывод прибыли | C8: Вывод прибыли (дивиденды)
A9: Закуп сырья | C9: Закуп сырья
A10: Вспомогательное сырье | B10: Закуп сырья | C10: Закуп сырья
A11: Основное сырье | B11: Закуп сырья | C11: Закуп сырья
A12: Сырье за наличные/бизнес карту | B12: Закуп сырья | C12: Закуп сырья
A13: Зарплата | C13: Зарплата
A14: Аванс | B14: Зарплата | C14: Зарплата
A15: Займ в счет зарплаты | B15: Зарплата | C15: Зарплата
A16: Зарплата | B16: Зарплата | C16: Зарплата
A17: Зарплата основная | B17: Зарплата | C17: Зарплата
A18: Отпускные | B18: Зарплата | C18: Зарплата
A19: Расчет при увольнении | B19: Зарплата | C19: Зарплата
A20: Фрилансы | B20: Зарплата | C20: Зарплата
A21: Канцтовары | C21: Канцтовары
A22: Командировочные расходы | C22: Командировочные
A23: Комиссия по эквайрингу | C23: Комиссия по эквайрингу
A24: Медосмотр и прививки | C24: Медосмотры
A25: Налоги на доходы (прибыль) | C25: Налог на доходы
A26: Налоги за сотрудников | C26: Налог ФОТ
A27: Взносы в фонды | B27: Налоги за сотрудников | C27: Налог ФОТ
A28: НДФЛ | B28: Налоги за сотрудников | C28: Налог ФОТ
A29: Неучтенные расходы | C29: Непредвиденные расходы
A30: Аренда гаража | C30: Оплата аренды и ВКУ
A31: Аренда объектов | C31: Оплата аренды и ВКУ
A32: Аренда объектов | B32: Аренда объектов | C32: Оплата аренды и ВКУ
A33: Аренда офиса | B33: Аренда объектов | C33: Оплата аренды и ВКУ
A34: Коммунальные расходы | B34: Аренда объектов | C34: Оплата аренды и ВКУ
A35: Официанты | C35: Официанты
A36: Платежи в бюджет | C36: Платежи в бюджет
A37: Выплата тела кредита | C37: Погашение кредитов
A38: Проценты по кредиту | C38: Погашение кредитов
A39: Поиск и найм персонала | C39: Поиск и найм персонала
A40: Представительские расходы | C40: Представительские расходы
A41: Производственные подрядчики | C41: Производственные подрядчики
A42: Производственный контроль (СЭС) | C42: Производственный контроль (СЭС)
A43: Расходы на программное обеспечение | C43: Расходы на программное обеспечение
A44: Рекламный бюджет | C44: Рекламный бюджет
A45: Бюджет на трафик | B45: Рекламный бюджет | C45: Рекламный бюджет
A46: Имиджевые расходы | B46: Рекламный бюджет | C46: Рекламный бюджет
A47: Косвенные маркетинговые расходы | B47: Рекламный бюджет | C47: Рекламный бюджет
A48: Ремонт объектов | C48: Содержание объектов
A49: Ремонт основных средств | C49: Содержание объектов
A50: Содержание объектов | C50: Содержание объектов
A51: Спецодежда | C51: Спецодежда
A52: Стратсессии | C52: Стратсессии
A53: Топливо | C53: Топливо
A54: Транспортные расходы | C54: Транспортные расходы
A55: Транспортные услуги | C55: Транспортные услуги
A56: Услуги связи и интернета | C56: Услуги связи и интернета
A57: Услуги сторонних подрядчиков | C57: Услуги сторонних подрядчиков
A58: Развоз персонала | C58: Услуги такси/Развоз персонала
A59: Услуги такси | C59: Услуги такси/Развоз персонала
... A79: Экспедиционные услуги | C79: Непредвиденные расходы

Sheet Сотношение
A1: Группа | B1: Направление | C1: Статья | D1: Род Статья
A2: Агентские вознаграждения | C2: Агентские вознаграждения
A3: Агрегаторы | C3: Агрегаторы
B4: Киви Фит | C4: Агрегаторы
A5: Банковское обслуживание | C5: Банковское обслуживание
A6: Комиссия по эквайрингу | C6: Комиссия по эквайрингу
B7: Кафе Вилюйск | C7: Комиссия по эквайрингу
A8: Налог на доходы
A9: Налог ФОТ
A10: Оплата аренды и ВКУ
A11: Погашение кредитов
A12: Расходы на программное обеспечение | C12: Расходы на программное обеспечение
B13: Кейтеринг | C13: Расходы на программное обеспечение
A14: Топливо | C14: Топливо
B15: Кафе Вилюйск | C15: Топливо
A16: Услуги связи и интернета | C16: Услуги связи и интернета
B17: Кафе Вилюйск | C17: Услуги связи и интернета
B18: Кейтеринг | C18: Услуги связи и интернета
B19: Офис Вилюйский тракт | C19: Услуги связи и интернета
A20: Услуги такси/Развоз персонала
A22: Возврат клиентам | C22: Возврат клиентам
B23: Айыы кыьата | C23: Возврат клиентам
B24: Кафе Вилюйск | C24: Возврат клиентам
B25: СОШ № 21 | C25: Возврат клиентам
B26: СОШ № 26 | C26: Возврат клиентам
B27: СОШ № 7 | C27: Возврат клиентам
A28: Вывод прибыли (дивиденды) | C28: Вывод прибыли
A29: Закуп сырья | C29: Вспомогательное сырье | D29: Закуп сырья
C30: Основное сырье | D30: Закуп сырья
C31: Сырье за наличные/бизнес карту | D31: Закуп сырья
B32: Айыы кыьата | C32: Сырье за наличные/бизнес карту | D32: Закуп сырья
B33: КТФ | C33: Основное сырье | D33: Закуп сырья
B34: Кафе Вилюйск | C34: Сырье за наличные/бизнес карту | D34: Закуп сырья
B35: Кейтеринг | C35: Вспомогательное сырье | D35: Закуп сырья
B36: РЦ | C36: Основное сырье | D36: Закуп сырья
A37: Зарплата | C37: Аванс | D37: Зарплата
C38: Зарплата основная | D38: Зарплата
C39: Отпускные | D39: Зарплата
C40: Расчет при увольнении | D40: Зарплата
C41: Фрилансы | D41: Зарплата
B42: АХО | C42: Аванс | D42: Зарплата
B43: АХО | C43: Зарплата основная | D43: Зарплата
B44: Айыы кыьата | C44: Аванс | D44: Зарплата
B45: Айыы кыьата | C45: Расчет при увольнении | D45: Зарплата
B46: Айыы кыьата | C46: Фрилансы | D46: Зарплата
B47: Ивент | C47: Аванс | D47: Зарплата
B48: Ивент | C48: Зарплата | D48: Зарплата
B49: Ивент | C49: Зарплата основная | D49: Зарплата
B50: Ивент | C50: Отпускные | D50: Зарплата
B51: Ивент | C51: Фрилансы | D51: Зарплата
B52: Кафе Вилюйск | C52: Аванс | D52: Зарплата
B53: Кафе Вилюйск | C53: Зарплата | D53: Зарплата
... B86: ЯРОД | C86: Зарплата основная | D86: Зарплата
A87: Кредиторка по аренде
A88: Кредиторка по рекламе
A89: Кредиторска по сырью
A90: Налоги ФОТ
A91: Официанты | C91: Официанты
B92: Кейтеринг | C92: Официанты
A93: Рекламный бюджет | C93: Бюджет на трафик | D93: Рекламный бюджет
C94: Имиджевые расходы | D94: Рекламный бюджет
C95: Косвенные маркетинговые расходы | D95: Рекламный бюджет
B96: Офис Вилюйский тракт | C96: Имиджевые расходы | D96: Рекламный бюджет
A97: Транспортные услуги | C97: Транспортные услуги
B98: Доставка | C98: Транспортные услуги
B99: Кафе Вилюйск | C99: Транспортные услуги
B100: Кейтеринг | C100: Транспортные услуги
B101: ЯРОД | C101: Транспортные услуги
A102: Транспортные расходы | C102: Транспортные расходы
B103: Автомобиль | C103: Транспортные расходы
A104: Фриланс | C104: Фрилансы | D104: Зарплата
B105: Айыы кыьата | C105: Фрилансы | D105: Зарплата
B106: Ивент | C106: Фрилансы | D106: Зарплата
B107: Кафе Вилюйск | C107: Фрилансы | D107: Зарплата
B108: Логистика | C108: Фрилансы | D108: Зарплата
B109: Окружное шоссе | C109: Фрилансы | D109: Зарплата
B110: РБ2 | C110: Фрилансы | D110: Зарплата
B111: РЦ | C111: Фрилансы | D111: Зарплата
B112: Речевая | C112: Фрилансы | D112: Зарплата
B113: СОШ № 21 | C113: Фрилансы | D113: Зарплата
A115: Административные подрядчики | C115: Административные подрядчики
A116: Канцтовары | C116: Канцтовары
A117: Командировочные | C117: Командировочные расходы
A118: Медосмотры
A119: ОС и ТМЦ
A120: Платежи в бюджет | C120: Платежи в бюджет
A121: Поиск и найм персонала | C121: Поиск и найм персонала
A122: Представительские расходы
A123: Производственные подрядчики
A124: Производственный контроль (СЭС)
A125: Содержание объектов | C125: Содержание объектов
B126: Айыы кыьата | C126: Содержание объектов
B127: Окружное шоссе | C127: Содержание объектов
B128: Офис Вилюйский тракт | C128: Содержание объектов
B129: РБ2 | C129: Содержание объектов
B130: РЦ | C130: Содержание объектов
B131: СОШ № 21 | C131: Содержание объектов
B132: СОШ № 26 | C132: Содержание объектов
B133: СОШ № 7 | C133: Содержание объектов
A134: Спецодежда | C134: Спецодежда
...

Sheet Лист2
A1: Аванс | B1: {=IFERROR(INDEX($F$1:$F$140,MATCH(A1,'Сотношение'!$C$1:$C$140,0)),IFERROR(INDEX($F$1:$F$140,MATCH(A1,$F$1:$F$140,0)),"НЕ НАЙДЕНО"))} -> Зарплата | F1: {=SCAN("",'Сотношение'!A1:A140,LAMBDA(acc,cur,IF(cur<>"",cur,acc)))} -> Группа
A2: Агентские вознаграждения | B2: {=IFERROR(INDEX($F$1:$F$140,MATCH(A2,'Сотношение'!$C$1:$C$140,0)),IFERROR(INDEX($F$1:$F$140,MATCH(A2,$F$1:$F$140,0)),"НЕ НАЙДЕНО"))} -> Агентские вознаграждения | F2: Агентские вознаграждения
A3: Агрегаторы | B3: {=IFERROR(INDEX($F$1:$F$140,MATCH(A3,'Сотношение'!$C$1:$C$140,0)),IFERROR(INDEX($F$1:$F$140,MATCH(A3,$F$1:$F$140,0)),"НЕ НАЙДЕНО"))} -> Агрегаторы | F3: Агрегаторы
A4: Административные подрядчики | B4: {=IFERROR(INDEX($F$1:$F$140,MATCH(A4,'Сотношение'!$C$1:$C$140,0)),IFERROR(INDEX($F$1:$F$140,MATCH(A4,$F$1:$F$140,0)),"НЕ НАЙДЕНО"))} -> Административные подрядчики | F4: Агрегаторы
A5: Аренда объектов | B5: {=IFERROR(INDEX($F$1:$F$140,MATCH(A5,'Сотношение'!$C$1:$C$140,0)),IFERROR(INDEX($F$1:$F$140,MATCH(A5,$F$1:$F$140,0)),"НЕ НАЙДЕНО"))} -> НЕ НАЙДЕНО | F5: Банковское обслуживание
A6: Банковское обслуживание | B6: {=IFERROR(INDEX($F$1:$F$140,MATCH(A6,'Сотношение'!$C$1:$C$140,0)),IFERROR(INDEX($F$1:$F$140,MATCH(A6,$F$1:$F$140,0)),"НЕ НАЙДЕНО"))} -> Банковское обслуживание | F6: Комиссия по эквайрингу
A7: Больничные | B7: {=IFERROR(INDEX($F$1:$F$140,MATCH(A7,'Сотношение'!$C$1:$C$140,0)),IFERROR(INDEX($F$1:$F$140,MATCH(A7,$F$1:$F$140,0)),"НЕ НАЙДЕНО"))} -> НЕ НАЙДЕНО | F7: Комиссия по эквайрингу
A8: Бюджет на трафик | B8: {=IFERROR(INDEX($F$1:$F$140,MATCH(A8,'Сотношение'!$C$1:$C$140,0)),IFERROR(INDEX($F$1:$F$140,MATCH(A8,$F$1:$F$140,0)),"НЕ НАЙДЕНО"))} -> Рекламный бюджет | F8: Налог на доходы
A9: Взносы в фонды | B9: {=IFERROR(INDEX($F$1:$F$140,MATCH(A9,'Сотношение'!$C$1:$C$140,0)),IFERROR(INDEX($F$1:$F$140,MATCH(A9,$F$1:$F$140,0)),"НЕ НАЙДЕНО"))} -> НЕ НАЙДЕНО | F9: Налог ФОТ
A10: Возврат внесенных средств собственника | B10: {=IFERROR(INDEX($F$1:$F$140,MATCH(A10,'Сотношение'!$C$1:$C$140,0)),IFERROR(INDEX($F$1:$F$140,MATCH(A10,$F$1:$F$140,0)),"НЕ НАЙДЕНО"))} -> НЕ НАЙДЕНО | F10: Оплата аренды и ВКУ
A11: Возврат клиентам | B11: {=IFERROR(INDEX($F$1:$F$140,MATCH(A11,'Сотношение'!$C$1:$C$140,0)),IFERROR(INDEX($F$1:$F$140,MATCH(A11,$F$1:$F$140,0)),"НЕ НАЙДЕНО"))} -> Возврат клиентам | F11: Погашение кредитов
A12: Вспомогательное сырье | B12: {=IFERROR(INDEX($F$1:$F$140,MATCH(A12,'Сотношение'!$C$1:$C$140,0)),IFERROR(INDEX($F$1:$F$140,MATCH(A12,$F$1:$F$140,0)),"НЕ НАЙДЕНО"))} -> Закуп сырья | F12: Расходы на программное обеспечение
A13: Вывод прибыли | B13: {=IFERROR(INDEX($F$1:$F$140,MATCH(A13,'Сотношение'!$C$1:$C$140,0)),IFERROR(INDEX($F$1:$F$140,MATCH(A13,$F$1:$F$140,0)),"НЕ НАЙДЕНО"))} -> Вывод прибыли (дивиденды) | F13: Расходы на программное обеспечение
... A49: Фрилансы | B49: {=IFERROR(INDEX($F$1:$F$140,MATCH(A49,'Сотношение'!$C$1:$C$140,0)),IFERROR(INDEX($F$1:$F$140,MATCH(A49,$F$1:$F$140,0)),"НЕ НАЙДЕНО"))} -> Зарплата | F49: Зарплата
A50: Экспедиционные услуги | F50: Зарплата
F51: Зарплата
F52: Зарплата
F53: Зарплата
F54: Зарплата
F55: Зарплата
F56: Зарплата
F57: Зарплата
F58: Зарплата
F59: Зарплата
F60: Зарплата
F61: Зарплата
F62: Зарплата
... F140: Непредвиденные расходы
